XGBoost_Ranking-0.7.0.dist-info/DESCRIPTION.rst
XGBoost_Ranking-0.7.0.dist-info/METADATA
XGBoost_Ranking-0.7.0.dist-info/RECORD
XGBoost_Ranking-0.7.0.dist-info/WHEEL
XGBoost_Ranking-0.7.0.dist-info/metadata.json
XGBoost_Ranking-0.7.0.dist-info/top_level.txt
xgboostextension/__init__.py
xgboostextension/xgbfeature.py
xgboostextension/xgbranker.py
