Metadata-Version: 2.0
Name: XGBoost-Ranking
Version: 0.7.0
Summary: XGBoost Extension for Easy Ranking & TreeFeature.
Home-page: https://github.com/bigdong89/xgboostExtension
Author: bigdong89
Author-email: dongjiaquan89@gmail.com
License: Apache 2.0
Platform: UNKNOWN
Requires-Dist: xgboost (>=0.7)
